MANIFEST.in
README.txt
setup.cfg
setup.py
Products/.DS_Store
Products/__init__.py
Products.remotefolder.egg-info/PKG-INFO
Products.remotefolder.egg-info/SOURCES.txt
Products.remotefolder.egg-info/dependency_links.txt
Products.remotefolder.egg-info/entry_points.txt
Products.remotefolder.egg-info/namespace_packages.txt
Products.remotefolder.egg-info/not-zip-safe
Products.remotefolder.egg-info/paster_plugins.txt
Products.remotefolder.egg-info/requires.txt
Products.remotefolder.egg-info/top_level.txt
Products/remotefolder/.DS_Store
Products/remotefolder/README.txt
Products/remotefolder/__init__.py
Products/remotefolder/config.py
Products/remotefolder/configure.zcml
Products/remotefolder/events.py
Products/remotefolder/browser/.DS_Store
Products/remotefolder/browser/__init__.py
Products/remotefolder/browser/configure.zcml
Products/remotefolder/browser/remotefolder_viewview.pt
Products/remotefolder/browser/remotefolder_viewview.py
Products/remotefolder/browser/updater.pt
Products/remotefolder/content/__init__.py
Products/remotefolder/content/configure.zcml
Products/remotefolder/content/remotefolder.py
Products/remotefolder/interfaces/__init__.py
Products/remotefolder/interfaces/remotefolder.py
Products/remotefolder/portlets/__init__.py
Products/remotefolder/portlets/configure.zcml
Products/remotefolder/profiles/.DS_Store
Products/remotefolder/profiles/default/.DS_Store
Products/remotefolder/profiles/default/factorytool.xml
Products/remotefolder/profiles/default/metadata.xml
Products/remotefolder/profiles/default/portlets.xml
Products/remotefolder/profiles/default/rolemap.xml
Products/remotefolder/profiles/default/types.xml
Products/remotefolder/profiles/default/types/Remote_Folder.xml
Products/remotefolder/tests/__init__.py
Products/remotefolder/tests/base.py
Products/remotefolder/tests/test_doctest.py
Products/remotefolder/tests/doctests/basicfunctionality.txt