Metadata-Version: 1.0
Name: Products.remotefolder
Version: 0.3
Summary: Folderish type that loads content from an external source like, for example, RSS feeds
Home-page: http://svn.collective.org/Products.remotefolder
Author: David Jonas
Author-email: david@v2.nl
License: GPL
Keywords: plone folderish folder type remote RSS feed
Platform: UNKNOWN
Classifier: Framework :: Plone
Classifier: Intended Audience :: Developers
Classifier: Topic :: Software Development :: Libraries :: Python Modules
Classifier: License :: OSI Approved :: GNU General Public License (GPL)
